{"cameraMode":{"drawMode":0,"name":"Shaded","section":"Shading Mode"},"sceneLighting":true,"audioPlay":false,"sceneViewState":{"showFog":true,"showMaterialUpdate":false,"showSkybox":true,"showFlares":true,"showImageEffects":true,"showParticleSystems":true},"in2DMode":false,"pivot":{"x":43.31526184082031,"y":1.0868759155273438,"z":-20.619937896728517},"rotation":{"x":-0.6724302768707275,"y":0.03149591013789177,"z":-0.028660789132118226,"w":-0.7389381527900696},"size":84.83934783935547,"orthographic":false}